README.md
setup.cfg
setup.py
raptorstr/__init__.py
raptorstr/formatting.py
raptorstr/levenshtein.py
raptorstr/validation.py
raptorstr.egg-info/PKG-INFO
raptorstr.egg-info/SOURCES.txt
raptorstr.egg-info/dependency_links.txt
raptorstr.egg-info/top_level.txt
tests/__init__.py
tests/common.py
tests/test_string_conversion.py
tests/test_string_tests.py