Metadata-Version: 1.1
Name: raptorstr
Version: 0.2.0
Summary: A package for working with strings with the purpose of generating code
Home-page: https://github.com/Mewongu/raptorstr
Author: Andreas Stenberg
Author-email: andreas@mewongu.com
License: UNKNOWN
Keywords: strings code case
Platform: UNKNOWN
Classifier: License :: OSI Approved :: Mozilla Public License 2.0 (MPL 2.0)
Classifier: Intended Audience :: Developers
